[

    {

        "nomeProduto": "Aero Daily Fitness Tee",
        "tamanho": "L",
        "cor": "Yellow",
        "quantidade": 9

    },

    {

        "nomeProduto": "Argus All-Weather Tank",
        "tamanho": "XL",
        "cor": "Gray",
        "quantidade": 2

    },

    {

        "nomeProduto": "Aether Gym Pant",
        "tamanho": "34",
        "cor": "Green",
        "quantidade": 5

    },

    {

        "nomeProduto": "Ariel Roll Sleeve Sweatshirt",
        "tamanho": "L",
        "cor": "Purple",
        "quantidade": 1

    }

]